 {
    "skillMetadata": {
        "sections": [
            {
                "name": "UE4 Light Skill Configuration",
                "fields": [
                    {
                        "name": "ip_address",
                        "type": "text",
                        "label": "The IP Address of the machine running Unreal Engine",
                        "value": "http://localhost"
                    },
                    {
                        "name": "bp_location",
                        "type": "text",
                        "label": "Location of the Lights Voice Control Blueprint",
                        "value": "/Game/Maps/Example_Map:PersistentLevel.UVE_Light_Control_BP_2"
                    }
                ]
            }
        ]
    }
}
